suitcase/json_metadata/__init__.py
suitcase/json_metadata/_version.py
suitcase/json_metadata/tests/__init__.py
suitcase/json_metadata/tests/conftest.py
suitcase/json_metadata/tests/tests.py
suitcase_json_metadata-0.2.1.dist-info/LICENSE
suitcase_json_metadata-0.2.1.dist-info/METADATA
suitcase_json_metadata-0.2.1.dist-info/WHEEL
suitcase_json_metadata-0.2.1.dist-info/entry_points.txt
suitcase_json_metadata-0.2.1.dist-info/top_level.txt
suitcase_json_metadata-0.2.1.dist-info/RECORD
